{
  "groups": [
    {
      "name": "cyan.tool.kit.generate.identity",
      "sourceType": "cyan.tool.kit.generate.starter.property.IdentityProperties",
      "type": "cyan.tool.kit.generate.starter.property.IdentityProperties"
    }
  ],
  "properties": [
    {
      "name": "cyan.tool.kit.generate.identity.workerId",
      "type": "java.lang.String",
      "description": "cyan.tool.kit.generate.identity.workerId."
    },
    {
      "name": "cyan.tool.kit.generate.identity.centerId",
      "type": "java.lang.String",
      "description": "cyan.tool.kit.generate.identity.centerId."
    }
  ] }